{"sections":{"slideshow_MbrLh8":{"type":"slideshow","blocks":{"slideshow_item_xtLdNA":{"type":"slideshow_item","settings":{"color_scheme":"dark","heading":"Slide heading","text":"<p>Text from here describes your slide<\/p>","button_label":"Button label","button_link":"","button_style":"primary","button_arrow":true,"overlay_enable":true,"overlay_opacity":20}},"slideshow_item_tP4XGC":{"type":"slideshow_item","settings":{"color_scheme":"dark","heading":"Slide heading","text":"<p>Text from here describes your slide<\/p>","button_label":"Button label","button_link":"","button_style":"primary","button_arrow":true,"overlay_enable":true,"overlay_opacity":20}},"slideshow_item_Vdcjyg":{"type":"slideshow_item","settings":{"color_scheme":"dark","heading":"Slide heading","text":"<p>Text from here describes your slide<\/p>","button_label":"Button label","button_link":"","button_style":"primary","button_arrow":true,"overlay_enable":true,"overlay_opacity":20}}},"block_order":["slideshow_item_xtLdNA","slideshow_item_tP4XGC","slideshow_item_Vdcjyg"],"settings":{"section_layout":"full","image_size":"large","is_autoplay":true,"is_hover_stop_autoplay":true,"show_arrows":true,"show_bullets":true,"slideshow_speed":1.1,"slideshow_delay":3,"parallax":true,"slide_effects":"slide","margin_top":0,"margin_bottom":0}},"main":{"type":"main-product","blocks":{"vendor":{"type":"vendor","settings":{"enable_vendor_link":false}},"title":{"type":"heading","settings":{}},"price":{"type":"price","settings":{}},"variant_picker":{"type":"variant_picker","settings":{"picker_type":"dropdown"}},"buy_buttons":{"type":"buy_buttons","settings":{"show_dynamic_checkout":true,"show_quantity":true,"show_gift_card_recipient":false}},"description_EaNL6y":{"type":"description","settings":{"description_heading":"Опис","default_open":true}},"popup":{"type":"popup","settings":{"label":"Pop-up link text","heading":"Popup heading","text":"<p>Some text<\/p>","page":""}},"pickup_availability":{"type":"pickup_availability","settings":{}},"complementary":{"type":"complementary","settings":{"product_list_limit":3}}},"block_order":["vendor","title","price","variant_picker","buy_buttons","description_EaNL6y","popup","pickup_availability","complementary"],"settings":{"desktop_alignment":"right","mobile_alignment":"before","image_gallery_collage":"thumbnail_carousel","mobile_image_gallery_collage":"thumbnail_carousel","show_thumbnail":true,"image_fit":"cover","image_ratio":"adapt","show_share":true,"show_share_facebook":true,"show_share_twitter":true,"show_share_pinterest":true,"show_share_copy":true}},"product-recommendations":{"type":"product-recommendations","settings":{"products_limit":4,"per_row":3,"mobile_card_count":false,"subheading":"subheading","heading":"Heading","button_label":"button label","button_link":"","image_ratio":"portrait","image_fit":"cover","show_secondary_image":false,"show_sku":false,"show_vendor":true,"show_desc":false,"padding_top":0,"padding_bottom":0,"margin_top":0,"margin_bottom":0,"enable_border_top":false,"enable_border_bottom":false}},"instagram-collage":{"type":"instagram-collage","settings":{"subheading":"Subheading","heading":"Heading","button_label":"Button label","icon_social":"instagram","button_link":"","column_per_row":4,"padding_top":20,"padding_bottom":20,"margin_top":0,"margin_bottom":80,"enable_border_top":false,"enable_border_bottom":false}}},"order":["slideshow_MbrLh8","main","product-recommendations","instagram-collage"]}